prefa/__init__.py
prefa/__version__.py
prefa/bintree.py
prefa/dfa.py
prefa/ere.py
prefa/fa.py
prefa/nfa.py
prefa/pgui.py
prefa/re.py
prefa-2.3.4.dist-info/DESCRIPTION.rst
prefa-2.3.4.dist-info/METADATA
prefa-2.3.4.dist-info/RECORD
prefa-2.3.4.dist-info/WHEEL
prefa-2.3.4.dist-info/metadata.json
prefa-2.3.4.dist-info/top_level.txt
