Metadata-Version: 2.0
Name: prefa
Version: 2.3.4
Summary: Presentation tool for Regular Expressions and Finite Automatas
Home-page: https://github.com/hgz12345ssdlh/prefa-master
Author: Jose, Robert & King
Author-email: huguanzhou123@sina.com
License: UNKNOWN
Platform: UNKNOWN
Classifier: Development Status :: 4 - Beta
Classifier: Intended Audience :: Education
Classifier: Intended Audience :: Developers
Classifier: Intended Audience :: Other Audience
Classifier: License :: OSI Approved :: MIT License
Classifier: Natural Language :: English
Classifier: Operating System :: POSIX
Classifier: Programming Language :: Python :: 3 :: Only
Classifier: Topic :: Utilities
Classifier: Topic :: Education
Classifier: Topic :: Adaptive Technologies
